kaaslibdinges/__init__.py
kaaslibdinges/nan/NaN.py
kaaslibdinges/nan/__init__.py
kaaslibdinges/visu/__init__.py
kaaslibdinges/visu/plot.py
kaaslibdinges-0.0.1.dist-info/LICENCE.txt
kaaslibdinges-0.0.1.dist-info/METADATA
kaaslibdinges-0.0.1.dist-info/WHEEL
kaaslibdinges-0.0.1.dist-info/top_level.txt
kaaslibdinges-0.0.1.dist-info/RECORD
