Metadata-Version: 2.1
Name: kaaslibdinges
Version: 0.0.1
Summary: very basic DS tools
Home-page: 
Author: Tim Oosterling
Author-email: 
License: MIT
Classifier: Development Status :: 5 - Production/Stable
Classifier: Intended Audience :: Education
Classifier: Operating System :: Microsoft :: Windows :: Windows 11
Classifier: License :: OSI Approved :: MIT License
Classifier: Programming Language :: Python :: 3
Requires-Python: >=2.7, !=3.0.*, !=3.1.*
License-File: LICENCE.txt
Requires-Dist: matplotlib (>=2.2.0)
